searchor/__init__.py
searchor/history.py
searchor/main.py
searchor-2.5.2.dist-info/LICENSE
searchor-2.5.2.dist-info/METADATA
searchor-2.5.2.dist-info/WHEEL
searchor-2.5.2.dist-info/entry_points.txt
searchor-2.5.2.dist-info/top_level.txt
searchor-2.5.2.dist-info/RECORD
