Metadata-Version: 2.1
Name: searchor
Version: 2.5.2
Summary: ⚡️ Quick and easy search engine queries.
Home-page: https://github.com/ArjunSharda/Searchor
Author: Arjun Sharda
Author-email: Arjun Sharda <sharda.aj17@gmail.com>, William Jackson <william@kegnh.com>
License: MIT License
Project-URL: Homepage, https://github.com/ArjunSharda/Searchor
Project-URL: Bug Tracker, https://github.com/ArjunSharda/Searchor/issues
Classifier: Programming Language :: Python :: 3
Classifier: License :: OSI Approved :: MIT License
Classifier: Operating System :: OS Independent
Requires-Python: >=3.7, <4
License-File: LICENSE
Requires-Dist: pyperclip
Requires-Dist: aenum
Requires-Dist: click
Requires-Dist: bs4
Requires-Dist: requests
